rcsb/__init__.py
rcsb/utils/__init__.py
rcsb/utils/multiproc/MultiProcLogging.py
rcsb/utils/multiproc/MultiProcPoolUtil.py
rcsb/utils/multiproc/MultiProcUtil.py
rcsb/utils/multiproc/__init__.py
rcsb_utils_multiproc-0.22.dist-info/METADATA
rcsb_utils_multiproc-0.22.dist-info/WHEEL
rcsb_utils_multiproc-0.22.dist-info/licenses/LICENSE
rcsb_utils_multiproc-0.22.dist-info/RECORD
